fundspy2021
