Metadata-Version: 2.1
Name: fundspy2021
Version: 1.3
Summary: Download brazillian investment funds and their benchmarks data from CVM and analyze their performance with pre-built functions.
Home-page: https://github.com/joaopm33/fundspy
Author: Joao Penido Monteiro
Author-email: joaopm33@gmail.com
License: MIT
Download-URL: https://github.com/joaopm33/fundspy/archive/refs/tags/v1.1.tar.gz
Keywords: INVESTMENTS,FUNDS,FINANCE,INVESTMENT FUNDS,BRAZILIAN ASSETS,HEDGE FUNDS,MUTUAL FUNDS
Platform: UNKNOWN
Classifier: Development Status :: 5 - Production/Stable
Classifier: Intended Audience :: Developers
Classifier: Intended Audience :: Education
Classifier: Intended Audience :: Financial and Insurance Industry
Classifier: Topic :: Office/Business :: Financial :: Investment
Classifier: License :: OSI Approved :: MIT License
Classifier: Programming Language :: Python :: 3
Classifier: Programming Language :: Python :: 3.4
Classifier: Programming Language :: Python :: 3.5
Classifier: Programming Language :: Python :: 3.6
Classifier: Programming Language :: Python :: 3.7
Classifier: Programming Language :: Python :: 3.8
